brainfall/__init__.py
brainfall/markets/__init__.py
brainfall/models/__init__.py
brainfall/models/binance.py
brainfall/models/candle_data.py
brainfall-0.1.4.dist-info/LICENSE
brainfall-0.1.4.dist-info/WHEEL
brainfall-0.1.4.dist-info/METADATA
brainfall-0.1.4.dist-info/RECORD
