Metadata-Version: 2.1
Name: brainfall
Version: 0.1.4
Summary: 
Author: EliaOnceAgain
Author-email: eabunassar@gmail.com
Requires-Python: >=3.10,<4.0
Classifier: Programming Language :: Python :: 3
Classifier: Programming Language :: Python :: 3.10
Classifier: Programming Language :: Python :: 3.11
Requires-Dist: binance-connector (>=1.18.0,<2.0.0)
Requires-Dist: pandas (>=1.5.1,<2.0.0)
